alchemite_apiclient/__init__.py
alchemite_apiclient/api_client.py
alchemite_apiclient/configuration.py
alchemite_apiclient/exceptions.py
alchemite_apiclient/extensions.py
alchemite_apiclient/model_utils.py
alchemite_apiclient/rest.py
alchemite_apiclient/api/__init__.py
alchemite_apiclient/api/datasets_api.py
alchemite_apiclient/api/default_api.py
alchemite_apiclient/api/jobs_api.py
alchemite_apiclient/api/metrics_api.py
alchemite_apiclient/api/model_dataset_api.py
alchemite_apiclient/api/models_api.py
alchemite_apiclient/api/projects_api.py
alchemite_apiclient/apis/__init__.py
alchemite_apiclient/calculated_columns/__init__.py
alchemite_apiclient/calculated_columns/formulae.py
alchemite_apiclient/calculated_columns/helpers.py
alchemite_apiclient/model/__init__.py
alchemite_apiclient/model/additive_sensitivity_request.py
alchemite_apiclient/model/analyse_validate_request.py
alchemite_apiclient/model/analyse_validate_request_all_of.py
alchemite_apiclient/model/analyse_validate_response.py
alchemite_apiclient/model/analyse_validate_response_column_analytics.py
alchemite_apiclient/model/categorical_column.py
alchemite_apiclient/model/categorical_column_info.py
alchemite_apiclient/model/categorical_column_info_all_of.py
alchemite_apiclient/model/categorical_column_info_stats.py
alchemite_apiclient/model/categorical_model_column_info.py
alchemite_apiclient/model/categorical_model_metrics.py
alchemite_apiclient/model/categorical_prediction.py
alchemite_apiclient/model/categorical_result.py
alchemite_apiclient/model/column_group_batch_request.py
alchemite_apiclient/model/column_group_patch_request.py
alchemite_apiclient/model/column_group_request.py
alchemite_apiclient/model/column_group_response.py
alchemite_apiclient/model/column_group_response_all_of.py
alchemite_apiclient/model/column_info.py
alchemite_apiclient/model/column_info_base.py
alchemite_apiclient/model/column_value.py
alchemite_apiclient/model/column_value_nullable.py
alchemite_apiclient-0.97.0.dist-info/licenses/LICENSE
alchemite_apiclient-0.97.0.dist-info/METADATA
alchemite_apiclient-0.97.0.dist-info/WHEEL
alchemite_apiclient-0.97.0.dist-info/top_level.txt
alchemite_apiclient-0.97.0.dist-info/RECORD
