Metadata-Version: 2.4
Name: alchemite_apiclient
Version: 0.97.0
Summary: A python API client for using Alchemite Analytics
Home-page: 
Author: Intellegens
Author-email: Intellegens <support@intellegens.com>
Project-URL: Homepage, https://intellegens.com
Project-URL: Docs, https://docs.intellegens.com
Keywords: Alchemite,Alchemite API,Machine Learning,Artificial Intelligence
Classifier: Development Status :: 5 - Production/Stable
Classifier: Programming Language :: Python :: 3
Classifier: License :: Other/Proprietary License
Classifier: Natural Language :: English
Classifier: Operating System :: OS Independent
Requires-Python: >=3.8
License-File: LICENSE
Requires-Dist: urllib3>=1.25.3
Requires-Dist: python-dateutil
Requires-Dist: oauthlib
Requires-Dist: requests>=2.22
Requires-Dist: requests-oauthlib
Requires-Dist: tqdm
Dynamic: author
Dynamic: license-file
Dynamic: requires-python
